provenaclient/__init__.py
provenaclient/auth/__init__.py
provenaclient/auth/helpers.py
provenaclient/auth/implementations.py
provenaclient/auth/manager.py
provenaclient/auth/py.typed
provenaclient/clients/README.md
provenaclient/clients/__init__.py
provenaclient/clients/auth_client.py
provenaclient/clients/client_helpers.py
provenaclient/clients/datastore_client.py
provenaclient/clients/id_service_client.py
provenaclient/clients/job_client.py
provenaclient/clients/prov_client.py
provenaclient/clients/py.typed
provenaclient/clients/registry_client.py
provenaclient/clients/search_client.py
provenaclient/clients/template_client.py
provenaclient/models/__init__.py
provenaclient/models/datastore.py
provenaclient/models/general.py
provenaclient/models/py.typed
provenaclient/modules/README.md
provenaclient/modules/__init__.py
provenaclient/modules/auth.py
provenaclient/modules/datastore.py
provenaclient/modules/id_service.py
provenaclient/modules/job_service.py
provenaclient/modules/link.py
provenaclient/modules/module_helpers.py
provenaclient/modules/prov.py
provenaclient/modules/provena_client.py
provenaclient/modules/py.typed
provenaclient/modules/registry.py
provenaclient/modules/search.py
provenaclient/modules/submodules/__init__.py
provenaclient/modules/submodules/datastore_io_submodule.py
provenaclient/modules/template_module.py
provenaclient/py.typed
provenaclient/utils/README.md
provenaclient/utils/__init__.py
provenaclient/utils/async_job_helpers.py
provenaclient/utils/config.py
provenaclient/utils/exceptions.py
provenaclient/utils/helpers.py
provenaclient/utils/http_client.py
provenaclient/utils/py.typed
provenaclient/utils/registry_endpoints.py
provenaclient-0.29.1.dist-info/LICENCE
provenaclient-0.29.1.dist-info/METADATA
provenaclient-0.29.1.dist-info/WHEEL
provenaclient-0.29.1.dist-info/RECORD
