Metadata-Version: 2.3
Name: provenaclient
Version: 0.29.1
Summary: A client library for interfacing with a Provena instance.
License: None
Author: RRAP
Author-email: rrapisdev@gmail.com
Requires-Python: >=3.9,<4.0
Classifier: License :: Other/Proprietary License
Classifier: Programming Language :: Python :: 3
Classifier: Programming Language :: Python :: 3.9
Classifier: Programming Language :: Python :: 3.10
Classifier: Programming Language :: Python :: 3.11
Classifier: Programming Language :: Python :: 3.12
Classifier: Programming Language :: Python :: 3.13
Requires-Dist: boto3 (==1.27.1)
Requires-Dist: cloudpathlib[s3] (==0.15.1)
Requires-Dist: httpx (>=0.27.0,<0.28.0)
Requires-Dist: provena-interfaces-v2 (>=2.10.5)
Requires-Dist: pydantic (>=2,<3)
Requires-Dist: python-jose (<3.3.0)
Requires-Dist: requests (>=2.26.0,<3.0.0)
